era_5g_relay_network_application/__init__.py
era_5g_relay_network_application/client.py
era_5g_relay_network_application/py.typed
era_5g_relay_network_application/server.py
era_5g_relay_network_application/utils.py
era_5g_relay_network_application/worker_clock.py
era_5g_relay_network_application/worker_commands.py
era_5g_relay_network_application/worker_image_publisher.py
era_5g_relay_network_application/worker_image_subscriber.py
era_5g_relay_network_application/worker_publisher.py
era_5g_relay_network_application/worker_service.py
era_5g_relay_network_application/worker_service_server.py
era_5g_relay_network_application/worker_socketio.py
era_5g_relay_network_application/worker_socketio_server.py
era_5g_relay_network_application/worker_subscriber.py
era_5g_relay_network_application/worker_tf.py
era_5g_relay_network_application/compatibility/__init__.py
era_5g_relay_network_application/compatibility/point_cloud_msg_conv.py
era_5g_relay_network_application/compatibility/rosbridge_action_loader.py
era_5g_relay_network_application/data/__init__.py
era_5g_relay_network_application/data/service.py
era_5g_relay_network_application/data/topic.py
era_5g_relay_network_application-1.5.0.dist-info/METADATA
era_5g_relay_network_application-1.5.0.dist-info/WHEEL
era_5g_relay_network_application-1.5.0.dist-info/namespace_packages.txt
era_5g_relay_network_application-1.5.0.dist-info/top_level.txt
era_5g_relay_network_application-1.5.0.dist-info/RECORD
