Metadata-Version: 2.1
Name: era-5g-relay-network-application
Version: 1.5.0
Summary: Relay Network Application
Author: Michal Kapinus
Author-email: ikapinus@fit.vutbr.cz
License: LGPL
Classifier: Programming Language :: Python :: 3
Classifier: License :: OSI Approved :: GNU Lesser General Public License v3 (LGPLv3)
Classifier: Operating System :: OS Independent
Classifier: Intended Audience :: Developers
Requires-Python: >=3.8
Requires-Dist: DracoPy (>=1.3.0)
Requires-Dist: era-5g-tf2json (~=0.2.0)
Requires-Dist: era-5g-client (~=1.0.0)
Requires-Dist: era-5g-interface (~=0.10.1)
Requires-Dist: era-5g-server (~=0.4.0)
Requires-Dist: numpy (>=1.24.4)
Requires-Dist: python-socketio[client] (>=5.11.1)
